tests
Motome
