Metadata-Version: 1.1
Name: Motome
Version: 0.2.2
Summary: Motome is a note taking and information aggregation application inspired by many other note taking programs.
Home-page: UNKNOWN
Author: Aaron Kehrer
Author-email: akehrer@in2being.com
License: BSD
Keywords: note-taking qt pyside  markdown
Platform: UNKNOWN
Classifier: Development Status :: 3 - Alpha
Classifier: Environment :: X11 Applications
Classifier: Environment :: MacOS X
Classifier: Environment :: Win32 (MS Windows)
Classifier: Topic :: Utilities
Classifier: License :: OSI Approved :: BSD License
